{"_via_settings":{"ui":{"annotation_editor_height":25,"annotation_editor_fontsize":0.8,"leftsidebar_width":18,"image_grid":{"img_height":80,"rshape_fill":"none","rshape_fill_opacity":0.3,"rshape_stroke":"yellow","rshape_stroke_width":2,"show_region_shape":true,"show_image_policy":"all"},"image":{"region_label":"__via_region_id__","region_color":"__via_default_region_color__","region_label_font":"10px Sans","on_image_annotation_editor_placement":"NEAR_REGION"}},"core":{"buffer_size":18,"filepath":{},"default_filepath":""},"project":{"name":"via_project_7Dec2022_12h40m"}},"_via_img_metadata":{"00000.image.png38371":{"filename":"00000.image.png","size":38371,"regions":[{"shape_attributes":{"name":"circle","cx":111,"cy":397,"r":43},"region_attributes":{"classes":"sphere"}},{"shape_attributes":{"name":"polygon","all_points_x":[117,122,145,173,170,141],"all_points_y":[291,321,333,317,287,275]},"region_attributes":{"classes":"cube"}}],"file_attributes":{}},"00001.image.png37889":{"filename":"00001.image.png","size":37889,"regions":[{"shape_attributes":{"name":"circle","cx":152,"cy":389,"r":42},"region_attributes":{"classes":"sphere"}},{"shape_attributes":{"name":"polygon","all_points_x":[156,161,162,195,195,191],"all_points_y":[281,299,321,322,291,277]},"region_attributes":{"classes":"cube"}}],"file_attributes":{}},"00002.image.png38547":{"filename":"00002.image.png","size":38547,"regions":[{"shape_attributes":{"name":"circle","cx":146,"cy":300,"r":32},"region_attributes":{"classes":"sphere"}},{"shape_attributes":{"name":"circle","cx":4,"cy":314,"r":18.248},"region_attributes":{"classes":"sphere"}},{"shape_attributes":{"name":"polygon","all_points_x":[151,151,162,189,185,177,149],"all_points_y":[229,255,262,258,227,219,226]},"region_attributes":{"classes":"cube"}}],"file_attributes":{}},"00003.image.png38377":{"filename":"00003.image.png","size":38377,"regions":[{"shape_attributes":{"name":"circle","cx":143,"cy":304,"r":19},"region_attributes":{"classes":"sphere"}},{"shape_attributes":{"name":"circle","cx":287,"cy":294,"r":34.132},"region_attributes":{"classes":"sphere"}},{"shape_attributes":{"name":"polygon","all_points_x":[263,263,284,301,302,281],"all_points_y":[222,251,257,250,223,215]},"region_attributes":{"classes":"cube"}}],"file_attributes":{}},"00004.image.png38437":{"filename":"00004.image.png","size":38437,"regions":[{"shape_attributes":{"name":"circle","cx":227,"cy":306,"r":18.439},"region_attributes":{"classes":"sphere"}},{"shape_attributes":{"name":"circle","cx":374,"cy":295,"r":33},"region_attributes":{"classes":"sphere"}},{"shape_attributes":{"name":"polygon","all_points_x":[330,329,343,367,371,353],"all_points_y":[220,247,258,253,226,215]},"region_attributes":{"classes":"cube"}}],"file_attributes":{}},"00005.image.png34016":{"filename":"00005.image.png","size":34016,"regions":[{"shape_attributes":{"name":"circle","cx":278,"cy":213,"r":27},"region_attributes":{"classes":"sphere"}},{"shape_attributes":{"name":"circle","cx":166,"cy":223,"r":14},"region_attributes":{"classes":"sphere"}},{"shape_attributes":{"name":"polyline","all_points_x":[262,263,277,291,291,281,262],"all_points_y":[167,187,183,187,171,163,169]},"region_attributes":{"classes":"cube"}}],"file_attributes":{}},"00006.image.png38506":{"filename":"00006.image.png","size":38506,"regions":[{"shape_attributes":{"name":"circle","cx":211,"cy":311,"r":19},"region_attributes":{"classes":"sphere"}},{"shape_attributes":{"name":"circle","cx":361,"cy":299,"r":31.064},"region_attributes":{"classes":"sphere"}},{"shape_attributes":{"name":"polygon","all_points_x":[321,321,344,358,361,334],"all_points_y":[229,261,266,254,226,220]},"region_attributes":{"classes":"cube"}}],"file_attributes":{}},"00007.image.png35821":{"filename":"00007.image.png","size":35821,"regions":[{"shape_attributes":{"name":"circle","cx":321,"cy":247,"r":32.311},"region_attributes":{"classes":"sphere"}},{"shape_attributes":{"name":"circle","cx":196,"cy":255,"r":14},"region_attributes":{"classes":"sphere"}},{"shape_attributes":{"name":"polygon","all_points_x":[291,293,302,324,326,318,294],"all_points_y":[191,214,216,215,194,186,188]},"region_attributes":{"classes":"cube"}}],"file_attributes":{}},"00008.image.png36838":{"filename":"00008.image.png","size":36838,"regions":[{"shape_attributes":{"name":"circle","cx":195,"cy":275,"r":17},"region_attributes":{"classes":"sphere"}},{"shape_attributes":{"name":"circle","cx":327,"cy":263,"r":30},"region_attributes":{"classes":"sphere"}},{"shape_attributes":{"name":"polygon","all_points_x":[299,299,307,333,333,324],"all_points_y":[203,235,235,229,208,198]},"region_attributes":{"classes":"cube"}}],"file_attributes":{}},"00009.image.png38901":{"filename":"00009.image.png","size":38901,"regions":[{"shape_attributes":{"name":"circle","cx":133,"cy":348,"r":41.012},"region_attributes":{"classes":"sphere"}},{"shape_attributes":{"name":"polygon","all_points_x":[134,139,156,183,182,163],"all_points_y":[257,287,297,282,255,247]},"region_attributes":{"classes":"cube"}}],"file_attributes":{}}},"_via_attributes":{"region":{"classes":{"type":"radio","description":"","options":{"sphere":"","cube":""},"default_options":{"cube":true}}},"file":{}},"_via_data_format_version":"2.0.10","_via_image_id_list":["00000.image.png38371","00001.image.png37889","00002.image.png38547","00003.image.png38377","00004.image.png38437","00005.image.png34016","00006.image.png38506","00007.image.png35821","00008.image.png36838","00009.image.png38901"]}